{
    "success": 1,
    "result": [
        {
            "id": "1",
            "name": "Лични нужди"
        },
        {
            "id": "2",
            "name": "Производствена дейност"
        },
        {
            "id": "3",
            "name": "Търговска дейност"
        },
        {
            "id": "4",
            "name": "Строителна дейност"
        },
        {
            "id": "5",
            "name": "Таксиметрови превози"
        },
        {
            "id": "6",
            "name": "Куриерска дейност"
        },
        {
            "id": "7",
            "name": "Друга фирмена дейност"
        },
        {
            "id": "8",
            "name": "Отдаване под наем"
        },
        {
            "id": "9",
            "name": "Учебен автомобил"
        },
        {
            "id": "10",
            "name": "Превоз на опасни товари"
        },
        {
            "id": "11",
            "name": "Състезателен автомобил"
        },
        {
            "id": "12",
            "name": "Специален режим на движение"
        },
        {
            "id": "13",
            "name": "Друго предназначение"
        }
    ]
}