{"Success":1,"result":[{"Id":"02717","Name":"Баня","PostCode":"4523"},{"Id":"07572","Name":"Бъта","PostCode":"4527"},{"Id":"27406","Name":"Елшица","PostCode":"4500"},{"Id":"22681","Name":"Левски","PostCode":"4500"},{"Id":"53103","Name":"Оборище","PostCode":"4522"},{"Id":"55302","Name":"Панагюрище","PostCode":"4500"},{"Id":"59375","Name":"Панагюрски колонии","PostCode":"4500"},{"Id":"57128","Name":"Поибрене","PostCode":"4524"},{"Id":"57580","Name":"Попинци","PostCode":"4528"},{"Id":"68271","Name":"Сребриново","PostCode":"4500"}]}